stacky/__init__.py
stacky/stacky.py
stacky/stacky_test.py
rockset_stacky-1.0.13.dist-info/LICENSE.txt
rockset_stacky-1.0.13.dist-info/METADATA
rockset_stacky-1.0.13.dist-info/WHEEL
rockset_stacky-1.0.13.dist-info/entry_points.txt
rockset_stacky-1.0.13.dist-info/top_level.txt
rockset_stacky-1.0.13.dist-info/RECORD
