Metadata-Version: 2.1
Name: rockset-stacky
Version: 1.0.13
Summary: stacky is a tool to manage stacks of PRs. This allows developers to easily 
Home-page: https://github.com/rockset/stacky
Author: Rockset
Author-email: tudor@rockset.com
Project-URL: Bug Reports, https://github.com/rockset/stacky/issues
Project-URL: Source, https://github.com/rockset/stacky
Keywords: github,stack,pr,pull request
Requires-Python: >=3.8, <4
License-File: LICENSE.txt
Requires-Dist: asciitree
Requires-Dist: ansicolors
Requires-Dist: simple-term-menu
